musig/__init__.py
musig/abstractclasses.py
musig/constants.py
musig/helpers.py
musig/nonce.py
musig/noncecommitment.py
musig/partialsignature.py
musig/protocol.py
musig/publickey.py
musig/signature.py
musig/signingsession.py
musig/singlesigkey.py
musig-0.0.1.dist-info/METADATA
musig-0.0.1.dist-info/WHEEL
musig-0.0.1.dist-info/RECORD
