Metadata-Version: 2.4
Name: musig
Version: 0.0.1
Summary: Implementation of the MuSig system for n-of-n multisignatures.
Project-URL: Homepage, https://github.com/k98kurz/musig
Project-URL: Bug Tracker, https://github.com/k98kurz/musig/issues
Author-email: k98kurz <k98kurz@gmail.com>
Classifier: Development Status :: 2 - Pre-Alpha
Classifier: License :: OSI Approved :: ISC License (ISCL)
Classifier: Operating System :: OS Independent
Classifier: Programming Language :: Python :: 3
Classifier: Topic :: Internet
Classifier: Topic :: Software Development :: Libraries :: Application Frameworks
Requires-Python: >=3.10
Requires-Dist: pynacl>=1.4.0
